BJA_plot_helpers/BJA_matplotlib_stylesheet.mplstyle
BJA_plot_helpers/__init__.py
BJA_plot_helpers/plot_utils.py
BJA_plot_helpers-0.2.dist-info/LICENSE
BJA_plot_helpers-0.2.dist-info/METADATA
BJA_plot_helpers-0.2.dist-info/WHEEL
BJA_plot_helpers-0.2.dist-info/top_level.txt
BJA_plot_helpers-0.2.dist-info/RECORD
