Metadata-Version: 2.1
Name: BJA-plot-helpers
Version: 0.2
Summary: Convenience functions for plotting with matplotlib and seaborn
License-File: LICENSE
Requires-Dist: pandas
Requires-Dist: numpy
Requires-Dist: matplotlib (>=3.5.0)
Requires-Dist: seaborn (>=0.10.0)
